models/HSAZLM.py
models/__init__.py
models/my_models.py
tools/__init__.py
tools/dataset.py
tools/plotting.py
tools/test.py
tools/tool.py
tools/train_eval_utils.py
train/__init__.py
train/main.py
train/predict.py
train/semantics.py
train/train.py
train/train_decae.py
train/train_fcnn.py
train/train_feature_extractor.py
ymszlm-0.0.11.dist-info/LICENSE
ymszlm-0.0.11.dist-info/METADATA
ymszlm-0.0.11.dist-info/WHEEL
ymszlm-0.0.11.dist-info/top_level.txt
ymszlm-0.0.11.dist-info/RECORD
