Metadata-Version: 2.2
Name: ymszlm
Version: 0.0.11
Summary: works
Author: yms
Author-email: 226000@qq.com
License-File: LICENSE
Dynamic: author
Dynamic: author-email
Dynamic: description
Dynamic: description-content-type
Dynamic: summary
